setup.py
segTrain/Fed.py
segTrain/__init__.py
segTrain/build.py
segTrain/train.py
segTrain.egg-info/PKG-INFO
segTrain.egg-info/SOURCES.txt
segTrain.egg-info/dependency_links.txt
segTrain.egg-info/top_level.txt
segTrain/configs/__init__.py
segTrain/configs/args.py
segTrain/configs/args1024.py
segTrain/dataset/__init__.py
segTrain/dataset/dataset.py
segTrain/dataset/dataset0.py
segTrain/losses/__init__.py
segTrain/losses/celoss.py
segTrain/losses/criterion.py
segTrain/losses/matcher.py
segTrain/losses/point_features.py
segTrain/model/__init__.py
segTrain/model/backbone/__init__.py
segTrain/model/backbone/checkpoint.py
segTrain/model/backbone/resnet.py
segTrain/model/backbone/swin4skysense.py
segTrain/model/backbone/swin_transformer.py
segTrain/model/semseg/GCM.py
segTrain/model/semseg/__init__.py
segTrain/model/semseg/base.py
segTrain/model/semseg/deeplabv2.py
segTrain/model/semseg/deeplabv3plus.py
segTrain/model/semseg/mask2former.py
segTrain/model/semseg/mask2former0.py
segTrain/model/semseg/mask2former_contextv1.py
segTrain/model/semseg/pspnet.py
segTrain/model/semseg/unetformer.py
segTrain/model/semseg/upernet.py
segTrain/model/semseg/lib_upernet/__init__.py
segTrain/model/semseg/lib_upernet/nn/__init__.py
segTrain/model/semseg/lib_upernet/nn/modules/__init__.py
segTrain/model/semseg/lib_upernet/nn/modules/batchnorm.py
segTrain/model/semseg/lib_upernet/nn/modules/comm.py
segTrain/model/semseg/lib_upernet/nn/modules/replicate.py
segTrain/model/semseg/lib_upernet/nn/modules/unittest.py
segTrain/model/semseg/lib_upernet/nn/parallel/__init__.py
segTrain/model/semseg/lib_upernet/nn/parallel/data_parallel.py
segTrain/model/semseg/lib_upernet/nn/prroi_pool/__init__.py
segTrain/model/semseg/lib_upernet/nn/prroi_pool/functional.py
segTrain/model/semseg/lib_upernet/nn/prroi_pool/prroi_pool.py
segTrain/model/semseg/lib_upernet/nn/prroi_pool/test_prroi_pooling2d.py
segTrain/model/semseg/utils_mask2former/__init__.py
segTrain/model/semseg/utils_mask2former/pixel_decoder/__init__.py
segTrain/model/semseg/utils_mask2former/pixel_decoder/msdeformattn.py
