Metadata-Version: 2.1
Name: segTrain
Version: 1.0.5
Summary: llm finetune
Author: mzd
Author-email: 1282032474@qq.com
Keywords: pip,segTrain
Platform: any
